[
  {
    "id": 1,
    "description": "Inspired by the unwavering spirit of the Filipino street dog, Azkal (AZK) rises above the chaos of the crypto world. This meme token embodies resilience and determination, offering a unique presence in a market of fleeting trends.",
    "price": "0.0000",
    "tokenCreated": "January 15, 2025",
    "image_url": "assets/app-logo/azkal.png",
    "image_url_cover": "assets/app-logo/AZKAL_LOGO.png",
    "network": "Xode",
    "network_id": "3"
  },
  {
    "id": 2,
    "description": "This meme token pays tribute to the legendary Manny Pacquiao, embodying his strength, resilience, and iconic Filipino pride. With a bold design inspired by the \"Pacman\" himself, it combines cultural heritage and innovation, making it a standout in the world of cryptocurrency.",
    "price": "0.0000",
    "tokenCreated": "January 15, 2025",
    "image_url": "assets/tokens/mpc.png",
    "image_url_cover": "assets/app-logo/Flag.png",
    "network": "Xode",
    "network_id": "7"
  }
]